ftrack_sftp_accessor/__init__.py
ftrack_sftp_accessor/_version.py
ftrack_sftp_accessor/sftp.py
LICENSE.txt
ftrack_sftp_accessor-0.5.1.dist-info/LICENSE.txt
ftrack_sftp_accessor-0.5.1.dist-info/METADATA
ftrack_sftp_accessor-0.5.1.dist-info/WHEEL
ftrack_sftp_accessor-0.5.1.dist-info/RECORD
